[{"name": "trec-spanish/trec3/queries", "url": "https://trec.nist.gov/data/topics_noneng/topics.SP1-SP25.spanish.english.gz", "time": "2025-08-17T08:10:52.816332", "duration": 0.3253505229949951, "result": "PASS", "fail_messagae": null, "md5": "22eea4a5c131db9cc4a431235f6a0573", "size": 9029, "recent_history": [{"result": "PASS", "time": "2025-05-04T08:11:52.728499"}, {"result": "PASS", "time": "2025-05-11T08:12:08.682374"}, {"result": "PASS", "time": "2025-05-18T08:12:17.723392"}, {"result": "PASS", "time": "2025-05-25T08:08:05.596953"}, {"result": "PASS", "time": "2025-06-01T08:08:08.835982"}, {"result": "PASS", "time": "2025-06-08T08:12:41.553390"}, {"result": "PASS", "time": "2025-06-15T08:10:15.919020"}, {"result": "PASS", "time": "2025-06-22T08:08:02.909641"}, {"result": "PASS", "time": "2025-06-29T08:07:55.563669"}, {"result": "PASS", "time": "2025-07-06T08:11:07.223133"}, {"result": "PASS", "time": "2025-07-13T08:12:39.431823"}, {"result": "PASS", "time": "2025-07-20T08:08:20.008687"}, {"result": "PASS", "time": "2025-07-27T08:14:07.987205"}, {"result": "PASS", "time": "2025-08-03T08:11:04.839732"}, {"result": "PASS", "time": "2025-08-10T08:08:28.385043"}, {"result": "PASS", "time": "2025-08-17T08:10:52.816332"}]}, {"name": "trec-spanish/trec3/qrels", "url": "https://trec.nist.gov/data/qrels_noneng/qrels.1-25.spanish.gz", "time": "2025-08-17T08:11:29.558855", "duration": 0.5435137748718262, "result": "PASS", "fail_messagae": null, "md5": "e1703487f43fb7ea30b87a0f14ccb5ce", "size": 64178, "recent_history": [{"result": "PASS", "time": "2025-05-11T08:13:20.106772"}, {"result": "PASS", "time": "2025-05-18T08:13:05.967008"}, {"result": "PASS", "time": "2025-05-25T08:09:12.226768"}, {"result": "PASS", "time": "2025-06-01T08:09:21.556054"}, {"result": "FAIL_BUT_HAS_MIRROR", "time": "2025-06-05T08:05:56.616036"}, {"result": "PASS", "time": "2025-06-08T08:13:24.217728"}, {"result": "PASS", "time": "2025-06-15T08:11:38.740168"}, {"result": "PASS", "time": "2025-06-22T08:09:22.811987"}, {"result": "PASS", "time": "2025-06-29T08:09:16.132977"}, {"result": "PASS", "time": "2025-07-06T08:12:10.393189"}, {"result": "PASS", "time": "2025-07-13T08:14:07.696636"}, {"result": "PASS", "time": "2025-07-20T08:08:55.582585"}, {"result": "PASS", "time": "2025-07-27T08:15:16.625581"}, {"result": "PASS", "time": "2025-08-03T08:12:35.129024"}, {"result": "PASS", "time": "2025-08-10T08:09:52.282491"}, {"result": "PASS", "time": "2025-08-17T08:11:29.558855"}]}, {"name": "trec-spanish/trec4/queries", "url": "https://trec.nist.gov/data/topics_noneng/topics.SP26-SP50.spanish.english.gz", "time": "2025-08-17T08:12:59.082102", "duration": 0.40218305587768555, "result": "PASS", "fail_messagae": null, "md5": "dfd9685cce559e33ab397c1878a6a1f8", "size": 2091, "recent_history": [{"result": "PASS", "time": "2025-05-04T08:14:08.978694"}, {"result": "PASS", "time": "2025-05-11T08:14:25.841085"}, {"result": "PASS", "time": "2025-05-18T08:14:08.060602"}, {"result": "PASS", "time": "2025-05-25T08:10:20.409605"}, {"result": "PASS", "time": "2025-06-01T08:10:36.345274"}, {"result": "PASS", "time": "2025-06-08T08:14:48.274281"}, {"result": "PASS", "time": "2025-06-15T08:12:43.590154"}, {"result": "PASS", "time": "2025-06-22T08:10:02.770078"}, {"result": "PASS", "time": "2025-06-29T08:10:07.483012"}, {"result": "PASS", "time": "2025-07-06T08:12:49.175682"}, {"result": "PASS", "time": "2025-07-13T08:15:25.685334"}, {"result": "PASS", "time": "2025-07-20T08:09:41.246903"}, {"result": "PASS", "time": "2025-07-27T08:16:42.101355"}, {"result": "PASS", "time": "2025-08-03T08:13:31.198321"}, {"result": "PASS", "time": "2025-08-10T08:11:11.640049"}, {"result": "PASS", "time": "2025-08-17T08:12:59.082102"}]}, {"name": "trec-spanish/trec4/qrels", "url": "https://trec.nist.gov/data/qrels_noneng/qrels.26-50.spanish.gz", "time": "2025-08-17T08:13:45.205128", "duration": 0.5397200584411621, "result": "PASS", "fail_messagae": null, "md5": "f2540f9fb83433ca8ef9503671136498", "size": 46394, "recent_history": [{"result": "PASS", "time": "2025-05-04T08:15:07.273037"}, {"result": "PASS", "time": "2025-05-11T08:15:20.096244"}, {"result": "PASS", "time": "2025-05-18T08:14:44.845397"}, {"result": "PASS", "time": "2025-05-25T08:11:46.317128"}, {"result": "PASS", "time": "2025-06-01T08:11:11.064208"}, {"result": "PASS", "time": "2025-06-08T08:16:08.134696"}, {"result": "PASS", "time": "2025-06-15T08:13:59.755781"}, {"result": "PASS", "time": "2025-06-22T08:10:55.889538"}, {"result": "PASS", "time": "2025-06-29T08:11:26.895605"}, {"result": "PASS", "time": "2025-07-06T08:14:04.743496"}, {"result": "PASS", "time": "2025-07-13T08:16:30.987820"}, {"result": "PASS", "time": "2025-07-20T08:10:43.206308"}, {"result": "PASS", "time": "2025-07-27T08:17:33.561082"}, {"result": "PASS", "time": "2025-08-03T08:14:57.628159"}, {"result": "PASS", "time": "2025-08-10T08:12:14.896540"}, {"result": "PASS", "time": "2025-08-17T08:13:45.205128"}]}]