[{"name": "trec-arabic/ar2001/queries", "url": "https://trec.nist.gov/data/topics_noneng/arabic_topics.txt", "time": "2023-10-11T08:05:46.060434", "duration": 0.623631477355957, "result": "FAIL_BUT_HAS_MIRROR", "fail_messagae": "Expected md5 hash to be a3d78c379056a080fe40a59a341496b8 but got ff4ed829ffd04e9c6095842b07d11f09", "md5": "a3d78c379056a080fe40a59a341496b8", "size": 107, "recent_history": [{"result": "PASS", "time": "2023-08-27T08:07:17.518433"}, {"result": "FAIL_BUT_HAS_MIRROR", "time": "2023-08-29T08:05:09.662401"}, {"result": "FAIL_BUT_HAS_MIRROR", "time": "2023-09-01T08:05:17.919198"}, {"result": "PASS", "time": "2023-09-03T08:07:04.431928"}, {"result": "FAIL_BUT_HAS_MIRROR", "time": "2023-09-06T08:05:23.888188"}, {"result": "FAIL_BUT_HAS_MIRROR", "time": "2023-09-08T08:05:13.597295"}, {"result": "PASS", "time": "2023-09-10T08:07:09.869534"}, {"result": "PASS", "time": "2023-09-17T08:07:15.559941"}, {"result": "FAIL_BUT_HAS_MIRROR", "time": "2023-09-18T08:05:38.058072"}, {"result": "PASS", "time": "2023-09-24T08:07:01.988342"}, {"result": "FAIL_BUT_HAS_MIRROR", "time": "2023-09-26T08:06:07.349708"}, {"result": "PASS", "time": "2023-10-01T08:07:22.537055"}, {"result": "FAIL_BUT_HAS_MIRROR", "time": "2023-10-03T08:05:18.776685"}, {"result": "PASS", "time": "2023-10-08T08:07:06.809412"}, {"result": "FAIL_BUT_HAS_MIRROR", "time": "2023-10-10T08:05:41.274695"}, {"result": "FAIL_BUT_HAS_MIRROR", "time": "2023-10-11T08:05:46.060434"}]}, {"name": "trec-arabic/ar2001/qrels", "url": "https://trec.nist.gov/data/qrels_noneng/xlingual_t10qrels.txt", "time": "2023-10-11T08:05:58.393352", "duration": 0.3197782039642334, "result": "FAIL_BUT_HAS_MIRROR", "fail_messagae": "Expected md5 hash to be 5951e2f0bf72df9f93fc32b93e3a7fde but got ff4ed829ffd04e9c6095842b07d11f09", "md5": "5951e2f0bf72df9f93fc32b93e3a7fde", "size": 107, "recent_history": [{"result": "PASS", "time": "2023-08-20T08:08:17.583409"}, {"result": "PASS", "time": "2023-08-27T08:08:05.030565"}, {"result": "FAIL_BUT_HAS_MIRROR", "time": "2023-08-29T08:05:21.301498"}, {"result": "FAIL_BUT_HAS_MIRROR", "time": "2023-09-01T08:05:27.821195"}, {"result": "PASS", "time": "2023-09-03T08:08:04.828981"}, {"result": "FAIL_BUT_HAS_MIRROR", "time": "2023-09-06T08:05:39.282051"}, {"result": "PASS", "time": "2023-09-10T08:07:41.771299"}, {"result": "PASS", "time": "2023-09-17T08:08:01.786266"}, {"result": "FAIL_BUT_HAS_MIRROR", "time": "2023-09-18T08:05:49.777563"}, {"result": "PASS", "time": "2023-09-24T08:08:15.858025"}, {"result": "FAIL_BUT_HAS_MIRROR", "time": "2023-09-26T08:06:14.998206"}, {"result": "PASS", "time": "2023-10-01T08:08:21.557746"}, {"result": "FAIL_BUT_HAS_MIRROR", "time": "2023-10-03T08:05:30.622166"}, {"result": "PASS", "time": "2023-10-08T08:07:46.124896"}, {"result": "FAIL_BUT_HAS_MIRROR", "time": "2023-10-10T08:05:54.433370"}, {"result": "FAIL_BUT_HAS_MIRROR", "time": "2023-10-11T08:05:58.393352"}]}, {"name": "trec-arabic/ar2002/queries", "url": "https://trec.nist.gov/data/topics_noneng/CL.topics.arabic.trec11.txt", "time": "2023-10-11T08:06:06.632246", "duration": 0.31623172760009766, "result": "FAIL_BUT_HAS_MIRROR", "fail_messagae": "Expected md5 hash to be f75a6164d794bab66509f1e818612363 but got ff4ed829ffd04e9c6095842b07d11f09", "md5": "f75a6164d794bab66509f1e818612363", "size": 107, "recent_history": [{"result": "PASS", "time": "2023-08-20T08:09:03.787095"}, {"result": "PASS", "time": "2023-08-27T08:08:53.301894"}, {"result": "FAIL_BUT_HAS_MIRROR", "time": "2023-08-29T08:05:30.850075"}, {"result": "FAIL_BUT_HAS_MIRROR", "time": "2023-09-01T08:05:37.570414"}, {"result": "PASS", "time": "2023-09-03T08:08:49.948713"}, {"result": "FAIL_BUT_HAS_MIRROR", "time": "2023-09-06T08:05:46.742903"}, {"result": "PASS", "time": "2023-09-10T08:09:01.759903"}, {"result": "PASS", "time": "2023-09-17T08:08:51.031952"}, {"result": "FAIL_BUT_HAS_MIRROR", "time": "2023-09-18T08:06:04.121263"}, {"result": "PASS", "time": "2023-09-24T08:08:50.974266"}, {"result": "FAIL_BUT_HAS_MIRROR", "time": "2023-09-26T08:06:22.834700"}, {"result": "PASS", "time": "2023-10-01T08:09:04.776164"}, {"result": "FAIL_BUT_HAS_MIRROR", "time": "2023-10-03T08:05:44.432343"}, {"result": "PASS", "time": "2023-10-08T08:09:11.573948"}, {"result": "FAIL_BUT_HAS_MIRROR", "time": "2023-10-10T08:06:01.281115"}, {"result": "FAIL_BUT_HAS_MIRROR", "time": "2023-10-11T08:06:06.632246"}]}, {"name": "trec-arabic/ar2002/qrels", "url": "https://trec.nist.gov/data/qrels_noneng/qrels.trec11.xlingual.txt", "time": "2023-10-11T08:06:16.890575", "duration": 0.3228442668914795, "result": "FAIL_BUT_HAS_MIRROR", "fail_messagae": "Expected md5 hash to be 40f25e1e98101e27d081685cbdc390ef but got ff4ed829ffd04e9c6095842b07d11f09", "md5": "40f25e1e98101e27d081685cbdc390ef", "size": 107, "recent_history": [{"result": "PASS", "time": "2023-08-20T08:10:07.681709"}, {"result": "PASS", "time": "2023-08-27T08:10:11.477716"}, {"result": "FAIL_BUT_HAS_MIRROR", "time": "2023-08-29T08:05:39.084585"}, {"result": "PASS", "time": "2023-09-03T08:09:39.248005"}, {"result": "FAIL_BUT_HAS_MIRROR", "time": "2023-09-06T08:05:53.996766"}, {"result": "PASS", "time": "2023-09-10T08:10:16.532595"}, {"result": "PASS", "time": "2023-09-17T08:10:18.479837"}, {"result": "FAIL_BUT_HAS_MIRROR", "time": "2023-09-18T08:06:13.207135"}, {"result": "PASS", "time": "2023-09-24T08:09:39.529661"}, {"result": "FAIL_BUT_HAS_MIRROR", "time": "2023-09-26T08:06:30.303230"}, {"result": "PASS", "time": "2023-10-01T08:10:06.973281"}, {"result": "FAIL_BUT_HAS_MIRROR", "time": "2023-10-03T08:05:52.856378"}, {"result": "FAIL_BUT_HAS_MIRROR", "time": "2023-10-05T08:06:42.960249"}, {"result": "PASS", "time": "2023-10-08T08:10:12.190049"}, {"result": "FAIL_BUT_HAS_MIRROR", "time": "2023-10-10T08:06:11.801201"}, {"result": "FAIL_BUT_HAS_MIRROR", "time": "2023-10-11T08:06:16.890575"}]}]